opuslib_next/__init__.py
opuslib_next/api/__init__.py
opuslib_next/api/ctl.py
opuslib_next/api/decoder.py
opuslib_next/api/encoder.py
opuslib_next/api/info.py
opuslib_next/classes.py
opuslib_next/constants.py
opuslib_next/exceptions.py
opuslib_next-1.1.5.dist-info/LICENSE
opuslib_next-1.1.5.dist-info/METADATA
opuslib_next-1.1.5.dist-info/WHEEL
opuslib_next-1.1.5.dist-info/RECORD
