Metadata-Version: 2.3
Name: opuslib_next
Version: 1.1.5
Summary: Python bindings to the libopus, IETF low-delay audio codec
License: BSD-3-Clause
Author: kalicyh
Author-email: kalicyh@qq.com
Requires-Python: >=3.10,<4.0
Classifier: License :: OSI Approved :: BSD License
Classifier: Programming Language :: Python :: 3
Classifier: Programming Language :: Python :: 3.10
Classifier: Programming Language :: Python :: 3.11
Classifier: Programming Language :: Python :: 3.12
Classifier: Programming Language :: Python :: 3.13
Project-URL: Documentation, https://github.com/kalicyh/opuslib-next
Project-URL: Homepage, https://github.com/kalicyh/opuslib-next
Project-URL: Repository, https://github.com/kalicyh/opuslib-next/issues
